skipulagsstofnun/__init__.py
skipulagsstofnun/plans.cpg
skipulagsstofnun/plans.dbf
skipulagsstofnun/plans.shp
skipulagsstofnun/plans.shx
skipulagsstofnun-0.2.1.dist-info/LICENSE
skipulagsstofnun-0.2.1.dist-info/WHEEL
skipulagsstofnun-0.2.1.dist-info/METADATA
skipulagsstofnun-0.2.1.dist-info/RECORD
