Metadata-Version: 2.1
Name: skipulagsstofnun
Version: 0.2.1
Summary: Library to lookup polygons, coordinates and metadata of approved local site plans in Iceland
Home-page: https://github.com/jokull/skipulagsstofnun
License: MIT
Author: Jökull Sólberg
Author-email: jokull@solberg.is
Requires-Python: >=3.7,<4.0
Classifier: License :: OSI Approved :: MIT License
Classifier: Programming Language :: Python :: 3
Classifier: Programming Language :: Python :: 3.10
Classifier: Programming Language :: Python :: 3.7
Classifier: Programming Language :: Python :: 3.8
Classifier: Programming Language :: Python :: 3.9
Requires-Dist: fiona (>=1.8.21,<2.0.0)
Requires-Dist: shapely (>=1.8.2,<2.0.0)
Project-URL: Repository, https://github.com/jokull/skipulagsstofnun
